APB_M/apb_master.v
`timescale 1ns/1ps
module apb_master(
	input		  PCLK,
	input		  PRESETn,

	output reg 	  PSEL,
	output reg 	  PENABLE,
	output reg [31:0] PADDR,
	output reg 	  PWRITE,
	output reg [31:0] PWDATA,

	input 	   [31:0] PRDATA,
	input 	   	  PREADY,
	input		  PSLVERR	
);

parameter NUM_TRANSFERS = 8;

localparam IDLE   = 2'b00;
localparam SETUP  = 2'b01;
localparam ACCESS = 2'b10;

reg [1:0] state,next_state;
reg [31:0] addr_reg, data_reg,read_reg;
reg write_reg,error_reg;
reg [3:0] transfer_count;

wire transfer;
assign transfer=(transfer_count < NUM_TRANSFERS);

// State Register
always @(posedge PCLK or negedge PRESETn)
	begin
	   if(!PRESETn)
	   	state <= IDLE;
	   else
		state <= next_state;
	end

always @(posedge PCLK or negedge PRESETn)
	begin
	  if(!PRESETn)
	    begin
		addr_reg <= 32'd0;
		data_reg <= 32'd0;
		write_reg <= 1'b0;
		read_reg  <= 32'd0;
		error_reg <= 1'b0;
		transfer_count <=4'd0;
	    end
	 else
	    begin
	     if(state==IDLE && transfer)
	      begin
		addr_reg  <= 32'h0000_0000;
		data_reg  <= 32'h1111_1111;
		write_reg <= 1'b1;
	      end
		
	else if(state==ACCESS && PREADY) 
	    begin
		if(!write_reg)
			read_reg <= PRDATA;
			error_reg <= PSLVERR;
			transfer_count <= transfer_count +1;
		if(transfer_count != NUM_TRANSFERS-1)
		  begin
			addr_reg <= addr_reg +4;
			data_reg <= data_reg +1;
			write_reg <= ~write_reg;
		  end
		end
		end
	  end
  
always @(*)
begin

    next_state = state;

    case(state)

        IDLE :
        begin
            if(transfer)
                next_state = SETUP;
            else
                next_state = IDLE;
        end

        SETUP :
        begin
            next_state = ACCESS;
        end

        ACCESS :
        begin

            if(!PREADY)
                next_state = ACCESS;

            else if(transfer_count == NUM_TRANSFERS)
                next_state = IDLE;

            else
                next_state = SETUP;

        end

        default :
            next_state = IDLE;

    endcase

end

always @(*)
begin

    PSEL = 1'b0;
    PENABLE = 1'b0;

    PADDR = 32'd0;
    PWRITE = 1'b0;
    PWDATA = 32'd0;

    case(state)

        IDLE :
        begin
            PSEL = 1'b0;
            PENABLE = 1'b0;
        end

        SETUP :
        begin
            PSEL = 1'b1;
            PENABLE = 1'b0;

            PADDR = addr_reg;
            PWRITE = write_reg;
            PWDATA = data_reg;
        end

        ACCESS :
        begin
            PSEL = 1'b1;
            PENABLE = 1'b1;

            PADDR = addr_reg;
            PWRITE = write_reg;
            PWDATA = data_reg;
        end

    endcase

end

endmodule

APB_M/apb_master_tb.v
`timescale 1ns/1ps

module apb_master_tb;

reg         PCLK;
reg         PRESETn;

wire        PSEL;
wire        PENABLE;
wire [31:0] PADDR;
wire        PWRITE;
wire [31:0] PWDATA;

reg  [31:0] PRDATA;
reg         PREADY;
reg         PSLVERR;

//------------------------------------------
// DUT
//------------------------------------------

apb_master dut
(
    .PCLK(PCLK),
    .PRESETn(PRESETn),

    .PSEL(PSEL),
    .PENABLE(PENABLE),
    .PADDR(PADDR),
    .PWRITE(PWRITE),
    .PWDATA(PWDATA),

    .PRDATA(PRDATA),
    .PREADY(PREADY),
    .PSLVERR(PSLVERR)
);

//------------------------------------------
// Clock Generation
//------------------------------------------

initial
begin
    PCLK = 0;
    forever #5 PCLK = ~PCLK;
end

//------------------------------------------
// Reset
//------------------------------------------

initial
begin
    PRESETn = 0;
    #20;
    PRESETn = 1;
end

//------------------------------------------
// Slave Model
//------------------------------------------

initial
begin
    PRDATA   = 32'h12345678;
    PREADY   = 1'b1;
    PSLVERR  = 1'b0;
end

//------------------------------------------
// Generate Wait States
//------------------------------------------

initial
begin

    #80;

    PREADY = 0;

    #30;

    PREADY = 1;

end

//------------------------------------------
// Generate Error
//------------------------------------------

initial
begin

    #170;

    PSLVERR = 1;

    #10;

    PSLVERR = 0;

end

//------------------------------------------
// Change Read Data
//------------------------------------------

always @(posedge PCLK)
begin

    if(PSEL && PENABLE && !PWRITE && PREADY)
        PRDATA <= PRDATA + 32'h10;

end

//------------------------------------------
// Monitor
//------------------------------------------

initial
begin

$display("---------------------------------------------------------------");
$display("TIME\tSTATE\tPSEL PENABLE PWRITE PADDR\t\tPWDATA\t\tPREADY");
$display("---------------------------------------------------------------");

$monitor("%0t\t%b\t%b\t%b\t%b\t%h\t%h\t%b",
        $time,
        dut.state,
        PSEL,
        PENABLE,
        PWRITE,
        PADDR,
        PWDATA,
        PREADY);

end

//------------------------------------------
// Dump Waveform
//------------------------------------------

initial
begin
    $dumpfile("apb_master.vcd");
    $dumpvars(0,apb_master_tb);
end

//------------------------------------------
// Finish Simulation
//------------------------------------------

initial
begin
    #400;
    $finish;
end

endmodule

APB_M/apb_master.vcd
$date
    Jul 22, 2026  05:49:59
$end
$version
    TOOL:	xmsim(64)	25.03-s001
$end
$timescale
    1 ps
$end

$scope module apb_master_tb $end
$var reg       1 !    PCLK $end
$var reg       1 "    PRESETn $end
$var wire      1 #    PSEL  $end
$var wire      1 $    PENABLE  $end
$var wire     32 %    PADDR [31:0] $end
$var wire      1 &    PWRITE  $end
$var wire     32 '    PWDATA [31:0] $end
$var reg      32 (    PRDATA [31:0] $end
$var reg       1 )    PREADY $end
$var reg       1 *    PSLVERR $end

$scope module dut $end
$var wire      1 +    PCLK  $end
$var wire      1 ,    PRESETn  $end
$var reg       1 -    PSEL $end
$var reg       1 .    PENABLE $end
$var reg      32 /    PADDR [31:0] $end
$var reg       1 0    PWRITE $end
$var reg      32 1    PWDATA [31:0] $end
$var wire     32 2    PRDATA [31:0] $end
$var wire      1 3    PREADY  $end
$var wire      1 4    PSLVERR  $end
$var parameter 32 5    NUM_TRANSFERS $end
$var parameter  2 6    IDLE $end
$var parameter  2 7    SETUP $end
$var parameter  2 8    ACCESS $end
$var reg       2 9    state [1:0] $end
$var reg       2 :    next_state [1:0] $end
$var reg      32 ;    addr_reg [31:0] $end
$var reg      32 <    data_reg [31:0] $end
$var reg      32 =    read_reg [31:0] $end
$var reg       1 >    write_reg $end
$var reg       1 ?    error_reg $end
$var reg       4 @    transfer_count [3:0] $end
$var wire      1 A    transfer  $end
$upscope $end

$upscope $end

$enddefinitions $end
$dumpvars
b10 8
b1 7
b0 6
b1000 5
0!
0"
0#
0$
b0 %
0&
b0 '
b10010001101000101011001111000 (
1)
0*
0+
0,
0-
0.
b0 /
00
b0 1
b10010001101000101011001111000 2
13
04
b0 9
b1 :
b0 ;
b0 <
b0 =
0>
0?
b0 @
1A
$end
#5000
1!
1+
#10000
0!
0+
#15000
1!
1+
#20000
1"
0!
0+
1,
#25000
1!
1+
b10001000100010001000100010001 <
1>
b1 9
1-
10
b10001000100010001000100010001 1
b10 :
b10001000100010001000100010001 '
1&
1#
#30000
0!
0+
#35000
1!
1+
b10 9
b1 :
0-
00
b0 1
1-
1.
10
b10001000100010001000100010001 1
1$
#40000
0!
0+
#45000
1!
1+
b1 @
b100 ;
b10001000100010001000100010010 <
0>
b1 9
b10 :
0-
0.
00
b0 1
1-
b100 /
b10001000100010001000100010010 1
b100 %
b10001000100010001000100010010 '
0&
0$
#50000
0!
0+
#55000
1!
1+
b10 9
b1 :
0-
b0 /
b0 1
1-
1.
b100 /
b10001000100010001000100010010 1
1$
#60000
0!
0+
#65000
1!
1+
b10010001101000101011010001000 (
b10010001101000101011001111000 =
b10 @
b1000 ;
b10001000100010001000100010011 <
1>
b1 9
b10 :
0-
0.
b0 /
b0 1
1-
b1000 /
10
b10001000100010001000100010011 1
1&
b10001000100010001000100010011 '
b1000 %
0$
b10010001101000101011010001000 2
#70000
0!
0+
#75000
1!
1+
b10 9
b1 :
0-
b0 /
00
b0 1
1-
1.
b1000 /
10
b10001000100010001000100010011 1
1$
#80000
0)
0!
0+
03
b10 :
#85000
1!
1+
#90000
0!
0+
#95000
1!
1+
#100000
0!
0+
#105000
1!
1+
#110000
1)
0!
0+
13
b1 :
#115000
1!
1+
b11 @
b1100 ;
b10001000100010001000100010100 <
0>
b1 9
b10 :
0-
0.
b0 /
00
b0 1
1-
b1100 /
b10001000100010001000100010100 1
b10001000100010001000100010100 '
0&
b1100 %
0$
#120000
0!
0+
#125000
1!
1+
b10 9
b1 :
0-
b0 /
b0 1
1-
1.
b1100 /
b10001000100010001000100010100 1
1$
#130000
0!
0+
#135000
1!
1+
b10010001101000101011010011000 (
b10010001101000101011010001000 =
b100 @
b10000 ;
b10001000100010001000100010101 <
1>
b1 9
b10 :
0-
0.
b0 /
b0 1
1-
b10000 /
10
b10001000100010001000100010101 1
1&
b10001000100010001000100010101 '
b10000 %
0$
b10010001101000101011010011000 2
#140000
0!
0+
#145000
1!
1+
b10 9
b1 :
0-
b0 /
00
b0 1
1-
1.
b10000 /
10
b10001000100010001000100010101 1
1$
#150000
0!
0+
#155000
1!
1+
b101 @
b10100 ;
b10001000100010001000100010110 <
0>
b1 9
b10 :
0-
0.
b0 /
00
b0 1
1-
b10100 /
b10001000100010001000100010110 1
b10001000100010001000100010110 '
0&
b10100 %
0$
#160000
0!
0+
#165000
1!
1+
b10 9
b1 :
0-
b0 /
b0 1
1-
1.
b10100 /
b10001000100010001000100010110 1
1$
#170000
1*
0!
0+
14
#175000
1!
1+
b10010001101000101011010101000 (
b10010001101000101011010011000 =
1?
b110 @
b11000 ;
b10001000100010001000100010111 <
1>
b1 9
b10 :
0-
0.
b0 /
b0 1
1-
b11000 /
10
b10001000100010001000100010111 1
1&
b10001000100010001000100010111 '
b11000 %
0$
b10010001101000101011010101000 2
#180000
0*
0!
0+
04
#185000
1!
1+
b10 9
b1 :
0-
b0 /
00
b0 1
1-
1.
b11000 /
10
b10001000100010001000100010111 1
1$
#190000
0!
0+
#195000
1!
1+
0?
b111 @
b11100 ;
b10001000100010001000100011000 <
0>
b1 9
b10 :
0-
0.
b0 /
00
b0 1
1-
b11100 /
b10001000100010001000100011000 1
b10001000100010001000100011000 '
0&
b11100 %
0$
#200000
0!
0+
#205000
1!
1+
b10 9
b1 :
0-
b0 /
b0 1
1-
1.
b11100 /
b10001000100010001000100011000 1
1$
#210000
0!
0+
#215000
1!
1+
b10010001101000101011010111000 (
b10010001101000101011010101000 =
b1000 @
b1 9
b10 :
0-
0.
b0 /
b0 1
1-
b11100 /
b10001000100010001000100011000 1
0$
0A
b10010001101000101011010111000 2
b1 :
b10 :
#220000
0!
0+
#225000
1!
1+
b10 9
b0 :
0-
b0 /
b0 1
1-
1.
b11100 /
b10001000100010001000100011000 1
1$
#230000
0!
0+
#235000
1!
1+
b10010001101000101011011001000 (
b10010001101000101011010111000 =
b1001 @
b100000 ;
b10001000100010001000100011001 <
1>
b0 9
0-
0.
b0 /
b0 1
b0 '
b0 %
0$
0#
b10010001101000101011011001000 2
